HISTORY.md
MANIFEST.in
README.md
pyproject.toml
environment/requirements.txt
src/projectoneflow/framework/__init__.py
src/projectoneflow/framework/ci/__init__.py
src/projectoneflow/framework/ci/cli.py
src/projectoneflow/framework/ci/comment/__init__.py
src/projectoneflow/framework/ci/comment/gitlab.py
src/projectoneflow/framework/cli/__init__.py
src/projectoneflow/framework/cli/blueprint.py
src/projectoneflow/framework/cli/cli.py
src/projectoneflow/framework/connector/__init__.py
src/projectoneflow/framework/connector/azure_blob.py
src/projectoneflow/framework/connector/databricks.py
src/projectoneflow/framework/contract/__init__.py
src/projectoneflow/framework/contract/project.py
src/projectoneflow/framework/contract/config/__init__.py
src/projectoneflow/framework/contract/config/objects.py
src/projectoneflow/framework/contract/env/__init__.py
src/projectoneflow/framework/contract/strategy/__init__.py
src/projectoneflow/framework/contract/strategy/deploy.py
src/projectoneflow/framework/exception/__init__.py
src/projectoneflow/framework/exception/ci.py
src/projectoneflow/framework/exception/connector.py
src/projectoneflow/framework/exception/contract.py
src/projectoneflow/framework/exception/deploy.py
src/projectoneflow/framework/exception/runner.py
src/projectoneflow/framework/runner/__init__.py
src/projectoneflow/framework/runner/databricks.py
src/projectoneflow/framework/runner/local.py
src/projectoneflow/framework/utils/__init__.py
src/projectoneflow/framework/validation/__init__.py
src/projectoneflow/framework/validation/data_objects.py
src/projectoneflow/framework/validation/pipeline.py
src/projectoneflow_framework.egg-info/PKG-INFO
src/projectoneflow_framework.egg-info/SOURCES.txt
src/projectoneflow_framework.egg-info/dependency_links.txt
src/projectoneflow_framework.egg-info/entry_points.txt
src/projectoneflow_framework.egg-info/requires.txt
src/projectoneflow_framework.egg-info/top_level.txt
tests/__init__.py
tests/unit_tests/__init__.py
tests/unit_tests/test_contract_env.py