Metadata-Version: 2.4
Name: projectoneflow-framework
Version: 1.0.0
Summary: This Project is wrapper for projectoneflow ingestion patterns
Author-email: Mukhesh Narra <narramukhesh@gmail.com>
Maintainer-email: Mukhesh Narra <narramukhesh@gmail.com>
License-Expression: MIT
Project-URL: bugs, https://github.com/narramukhesh/projectone/issues
Project-URL: changelog, https://github.com/narramukhesh/projectone/tree/main/projectoneflow-framework/HISTORY.md
Project-URL: homepage, https://github.com/narramukhesh/projectone/tree/main/projectoneflow-framework
Keywords: dataengineering,projectoneflow,pyspark,delta-lake,Python
Classifier: Development Status :: 5 - Production/Stable
Classifier: Natural Language :: English
Classifier: Intended Audience :: Developers
Classifier: Topic :: Software Development
Requires-Python: >=3.10
Requires-Dist: projectoneflow
Requires-Dist: rich==13.9.4
Requires-Dist: databricks-sdk==0.38.0
Requires-Dist: azure-identity==1.19.0
Requires-Dist: azure-storage-blob==12.24.1
Requires-Dist: sqlparse==0.5.3
